[
  {
    "videoId": "05551140012016213318",
    "videoName": "Martin",
    "subtitles": [
      {
        "id": "70e163b3-490d-08de-6245-3fe5498eb3bf",
        "startTime": 227.392785,
        "endTime": 229.993572,
        "txt": "dasdsadsad",
        "totalVotes": 1
      },
      {
        "id": "6a9ac999-0247-18ec-2455-c61fef3d9f61",
        "startTime": 219.168446,
        "endTime": 227.392785,
        "txt": "dsadsadsadsadsa",
        "totalVotes": 0
      },
      {
        "id": "0625e719-911c-182b-1075-220d90837f70",
        "startTime": 209.42686,
        "endTime": 219.168446,
        "txt": "3123213213131",
        "totalVotes": 1
      },
      {
        "id": "1931537b-d3d3-c511-3deb-2e81df6718f8",
        "startTime": 208.634232,
        "endTime": 209.42686,
        "txt": "15615165",
        "totalVotes": 0
      },
      {
        "id": "5b281116-cd9c-9499-56f9-9418ec759546",
        "startTime": 1.445391,
        "endTime": 208.634232,
        "txt": "jnjn]\\",
        "totalVotes": 0
      },
      {
        "startTime": "0",
        "endTime": 1.445391,
        "txt": "What brings you to the landof the gatekeepers?",
        "length": "",
        "totalVotes": 5
      }
    ],
    "remarks": [
      {
        "id": "db6e1f96-3a01-5602-486e-b2b832ae9f4c",
        "startTime": 289.584282,
        "endTime": 293.305352,
        "txt": "dasdsad",
        "totalVotes": 1
      },
      {
        "id": "aac2aff4-ee98-c249-64c2-46cd078ce118",
        "startTime": 2.689828,
        "endTime": 4.690445,
        "txt": "dsadsadddd",
        "totalVotes": 1
      },
      {
        "id": "15cc1c5d-c062-4e2f-192d-b55d301b3841",
        "startTime": 1.190256,
        "endTime": 2.689828,
        "txt": "dsadsadasdsa",
        "totalVotes": -1
      }
    ],
    "userrr": {
      "subtitles": [
        {
          "id": "e6b7ce18-873c-d23e-6b51-c54c05428cf2",
          "startTime": 999.907211,
          "endTime": 1002.656341,
          "txt": "ddsadada",
          "totalVotes": 0
        },
        {
          "id": "715790ed-acbf-12de-1dfc-3ca5f4c37b5d",
          "startTime": 998.153545,
          "endTime": 999.907211,
          "txt": "dsadadsadsa",
          "totalVotes": 0
        },
        {
          "id": "1dbfdc0a-f4cd-c8ad-3dd6-2db23de9688e",
          "startTime": 996.160056,
          "endTime": 998.153545,
          "txt": "dsadsadsasa",
          "totalVotes": 0
        },
        {
          "id": "0f8b9627-ae86-e960-2391-70e388c2f89a",
          "startTime": 1.198942,
          "endTime": 1.540286,
          "txt": "sadsadsadadsa",
          "totalVotes": 0
        },
        {
          "id": "fb979efb-4e57-c313-c7fd-f94a9c2618bb",
          "startTime": 0.941996,
          "endTime": 1.198942,
          "txt": "sadsa",
          "totalVotes": 0
        },
        {
          "id": "e2152171-3cb8-051a-88d4-53e1fd577629",
          "startTime": 0,
          "endTime": 0.941996,
          "txt": "dsadsadsad",
          "totalVotes": 0
        }
      ],
      "remarks": [
        {
          "id": "a4d0cf30-820c-223d-ceb0-5b5f854350bf",
          "startTime": 37.834408,
          "endTime": 38.114205,
          "txt": "dsa",
          "totalVotes": 0
        },
        {
          "id": "03c358cb-8c3b-6c63-34cf-5302027b0474",
          "startTime": 37.31307,
          "endTime": 37.834408,
          "txt": "dsa",
          "totalVotes": 0
        },
        {
          "id": "c2b05559-9d01-2019-b402-92b0d2838815",
          "startTime": 36.99072,
          "endTime": 37.31307,
          "txt": "dsadsadsa",
          "totalVotes": 0
        },
        {
          "id": "771bdbde-4c82-9bc1-f235-1d477449c6ce",
          "startTime": 36.706722,
          "endTime": 36.99072,
          "txt": "dsadsa",
          "totalVotes": 0
        },
        {
          "id": "81253b07-128d-d092-fedd-6880579b45b9",
          "startTime": 36.270203,
          "endTime": 36.706722,
          "txt": "dsadsa",
          "totalVotes": 0
        },
        {
          "id": "5604b9f6-75ce-c011-919e-e951a2e2c268",
          "startTime": 35.95981,
          "endTime": 36.270203,
          "txt": "dsadsa",
          "totalVotes": 0
        },
        {
          "id": "7bf4f461-96fd-84ab-79a0-fb84d935137b",
          "startTime": 35.439893,
          "endTime": 35.95981,
          "txt": "sdsadsadsa",
          "totalVotes": 0
        },
        {
          "id": "efa5bfe8-16e4-c63c-b226-7c3bfa61ce21",
          "startTime": 34.729068,
          "endTime": 35.439893,
          "txt": "sadsad",
          "totalVotes": 0
        },
        {
          "id": "613775a0-0093-b0f6-2bb2-30db0b1614e1",
          "startTime": 34.441264,
          "endTime": 34.729068,
          "txt": "sadsa",
          "totalVotes": 0
        },
        {
          "id": "fede7968-16a5-e2c8-b309-5147bca45410",
          "startTime": 0,
          "endTime": 34.441264,
          "txt": "dsadsad",
          "totalVotes": 0
        }
      ]
    }
  }
]
